{
    "Ar36": {
        "error": 0.00028751304140555426,
        "error_type": "SEM",
        "filter_outliers_dict": {
            "filter_outliers": true,
            "iterations": 1,
            "std_devs": 3,
            "use_iqr_filtering": false,
            "use_standard_deviation_filtering": false
        },
        "fit": "linear",
        "fn": 298,
        "include_baseline_error": true,
        "n": 300,
        "outlier_excluded": [
            1,
            171
        ],
        "reviewed": true,
        "user_excluded": [],
        "value": 0.03141893256047475
    },
    "Ar37": {
        "error": 0.003914128356078092,
        "error_type": "SEM",
        "filter_outliers_dict": {
            "filter_outliers": true,
            "iterations": 1,
            "std_devs": 3,
            "use_iqr_filtering": false,
            "use_standard_deviation_filtering": false
        },
        "fit": "linear",
        "fn": 299,
        "include_baseline_error": true,
        "n": 300,
        "outlier_excluded": [
            168
        ],
        "reviewed": true,
        "user_excluded": [],
        "value": 0.022415519356230734
    },
    "Ar38": {
        "error": 0.0032197973503779987,
        "error_type": "SEM",
        "filter_outliers_dict": {
            "filter_outliers": true,
            "iterations": 1,
            "std_devs": 3,
            "use_iqr_filtering": false,
            "use_standard_deviation_filtering": false
        },
        "fit": "linear",
        "fn": 298,
        "include_baseline_error": true,
        "n": 300,
        "outlier_excluded": [
            224,
            186
        ],
        "reviewed": true,
        "user_excluded": [],
        "value": 0.35519350684404144
    },
    "Ar39": {
        "error": 0.01466388120602475,
        "error_type": "SEM",
        "filter_outliers_dict": {
            "filter_outliers": true,
            "iterations": 1,
            "std_devs": 3,
            "use_iqr_filtering": false,
            "use_standard_deviation_filtering": false
        },
        "fit": "parabolic",
        "fn": 300,
        "include_baseline_error": true,
        "n": 300,
        "outlier_excluded": [],
        "reviewed": true,
        "user_excluded": [],
        "value": 23.10519696956797
    },
    "Ar40": {
        "error": 0.021316533651828784,
        "error_type": "SEM",
        "filter_outliers_dict": {
            "filter_outliers": true,
            "iterations": 1,
            "std_devs": 3,
            "use_iqr_filtering": false,
            "use_standard_deviation_filtering": false
        },
        "fit": "parabolic",
        "fn": 298,
        "include_baseline_error": true,
        "n": 300,
        "outlier_excluded": [
            107,
            171
        ],
        "reviewed": true,
        "user_excluded": [],
        "value": 118.1748039470937
    },
    "Ar41": {
        "error": 0.0028328675988162706,
        "error_type": "SEM",
        "filter_outliers_dict": {
            "filter_outliers": true,
            "iterations": 1,
            "std_devs": 2
        },
        "fit": "average",
        "value": 0.07780150785417304
    }
}