{
    "AX": {
        "error": 0.007878811003328602,
        "error_type": "SEM",
        "filter_outliers_dict": {
            "filter_outliers": true,
            "iterations": 1,
            "std_devs": 3,
            "use_iqr_filtering": false,
            "use_standard_deviation_filtering": false
        },
        "fit": "average",
        "fn": 60,
        "include_baseline_error": false,
        "n": 60,
        "outlier_excluded": [],
        "reviewed": true,
        "user_excluded": [],
        "value": -0.0493034070697225
    },
    "CDD": {
        "error": 8.099090454690963e-06,
        "error_type": "SEM",
        "filter_outliers_dict": {
            "filter_outliers": true,
            "iterations": 1,
            "std_devs": 10,
            "use_iqr_filtering": false,
            "use_standard_deviation_filtering": false
        },
        "fit": "average",
        "fn": 60,
        "include_baseline_error": false,
        "n": 60,
        "outlier_excluded": [],
        "reviewed": true,
        "user_excluded": [],
        "value": 2.3268344375537708e-05
    },
    "H1": {
        "error": 0.0058665597438525615,
        "error_type": "SEM",
        "filter_outliers_dict": {
            "filter_outliers": true,
            "iterations": 1,
            "std_devs": 3,
            "use_iqr_filtering": false,
            "use_standard_deviation_filtering": false
        },
        "fit": "average",
        "fn": 60,
        "include_baseline_error": false,
        "n": 60,
        "outlier_excluded": [],
        "reviewed": true,
        "user_excluded": [],
        "value": 0.13447358595828215
    },
    "H2": {
        "error": 0.036622434072250895,
        "error_type": "SEM",
        "filter_outliers_dict": {
            "filter_outliers": true,
            "iterations": 1,
            "std_devs": 3,
            "use_iqr_filtering": false,
            "use_standard_deviation_filtering": false
        },
        "fit": "average",
        "fn": 59,
        "include_baseline_error": false,
        "n": 60,
        "outlier_excluded": [
            22
        ],
        "reviewed": true,
        "user_excluded": [],
        "value": -0.552366504879763
    },
    "L1": {
        "error": 0.0039551785451250885,
        "error_type": "SEM",
        "filter_outliers_dict": {
            "filter_outliers": true,
            "iterations": 1,
            "std_devs": 3,
            "use_iqr_filtering": false,
            "use_standard_deviation_filtering": false
        },
        "fit": "average",
        "fn": 59,
        "include_baseline_error": false,
        "n": 60,
        "outlier_excluded": [
            0
        ],
        "reviewed": true,
        "user_excluded": [],
        "value": 0.02042940962404581
    },
    "L2": {
        "error": 0.0038632110093869275,
        "error_type": "SEM",
        "filter_outliers_dict": {
            "filter_outliers": true,
            "iterations": 1,
            "std_devs": 3
        },
        "fit": "average",
        "value": -0.0031325819622051226
    }
}