{
    "Ar36": {
        "error": 0.0004378679583764525,
        "error_type": "SEM",
        "filter_outliers_dict": {
            "filter_outliers": true,
            "iterations": 2,
            "std_devs": 2,
            "use_iqr_filtering": false,
            "use_standard_deviation_filtering": false
        },
        "fit": "linear",
        "fn": 318,
        "include_baseline_error": true,
        "n": 340,
        "outlier_excluded": [
            143,
            16,
            275,
            151,
            29,
            157,
            160,
            34,
            38,
            169,
            171,
            175,
            321,
            70,
            337,
            226,
            102,
            104,
            235,
            109,
            117,
            248
        ],
        "reviewed": true,
        "user_excluded": [],
        "value": 0.09826109990672528
    },
    "Ar37": {
        "error": 0.006472881411953865,
        "error_type": "SEM",
        "filter_outliers_dict": {
            "filter_outliers": true,
            "iterations": 2,
            "std_devs": 2,
            "use_iqr_filtering": false,
            "use_standard_deviation_filtering": false
        },
        "fit": "linear",
        "fn": 316,
        "include_baseline_error": true,
        "n": 340,
        "outlier_excluded": [
            0,
            131,
            7,
            10,
            142,
            281,
            29,
            31,
            293,
            295,
            45,
            174,
            176,
            177,
            62,
            202,
            337,
            217,
            226,
            227,
            101,
            107,
            114,
            115
        ],
        "reviewed": true,
        "user_excluded": [],
        "value": 1.2484599945006027
    },
    "Ar38": {
        "error": 0.00023839221637785295,
        "error_type": "SEM",
        "filter_outliers_dict": {
            "filter_outliers": true,
            "iterations": 2,
            "std_devs": 2,
            "use_iqr_filtering": false,
            "use_standard_deviation_filtering": false
        },
        "fit": "linear",
        "fn": 322,
        "include_baseline_error": true,
        "n": 340,
        "outlier_excluded": [
            65,
            3,
            197,
            5,
            200,
            41,
            42,
            203,
            174,
            240,
            17,
            274,
            52,
            308,
            119,
            186,
            157,
            159
        ],
        "reviewed": true,
        "user_excluded": [],
        "value": 0.028544920602680025
    },
    "Ar39": {
        "error": 0.0070960867546195966,
        "error_type": "SEM",
        "filter_outliers_dict": {
            "filter_outliers": true,
            "iterations": 2,
            "std_devs": 2,
            "use_iqr_filtering": false,
            "use_standard_deviation_filtering": false
        },
        "fit": "linear",
        "fn": 314,
        "include_baseline_error": true,
        "n": 340,
        "outlier_excluded": [
            7,
            10,
            11,
            270,
            153,
            156,
            284,
            168,
            170,
            42,
            300,
            323,
            195,
            324,
            201,
            331,
            210,
            212,
            218,
            98,
            231,
            108,
            114,
            115,
            246,
            123
        ],
        "reviewed": true,
        "user_excluded": [],
        "value": 0.5370661643427236
    },
    "Ar40": {
        "error": 0.02710504353438564,
        "error_type": "SEM",
        "filter_outliers_dict": {
            "filter_outliers": true,
            "iterations": 2,
            "std_devs": 2,
            "use_iqr_filtering": false,
            "use_standard_deviation_filtering": false
        },
        "fit": "parabolic",
        "fn": 316,
        "include_baseline_error": true,
        "n": 340,
        "outlier_excluded": [
            256,
            257,
            2,
            7,
            136,
            264,
            150,
            152,
            284,
            41,
            42,
            176,
            308,
            310,
            206,
            80,
            338,
            88,
            92,
            105,
            106,
            240,
            121,
            127
        ],
        "reviewed": true,
        "user_excluded": [],
        "value": 32.44194825803176
    }
}