{
    "AX": {
        "error": 0.008501119927795855,
        "error_type": "SEM",
        "filter_outliers_dict": {
            "filter_outliers": true,
            "iterations": 1,
            "std_devs": 2
        },
        "fit": "average",
        "modifier_error": 0.0,
        "modifier_value": 0.0,
        "value": -0.20428895302260106
    },
    "CDD": {
        "error": 1.1507502548627226e-05,
        "error_type": "SEM",
        "filter_outliers_dict": {
            "filter_outliers": true,
            "iterations": 1,
            "std_devs": 10
        },
        "fit": "average",
        "modifier_error": 9.53795368954982e-06,
        "modifier_value": 2.0551611207295713e-05,
        "value": 5.707605824831607e-05
    },
    "H1": {
        "error": 0.007094704305306597,
        "error_type": "SEM",
        "filter_outliers_dict": {
            "filter_outliers": true,
            "iterations": 1,
            "std_devs": 2
        },
        "fit": "average",
        "modifier_error": 0.0,
        "modifier_value": 0.0,
        "value": -0.011156978626618814
    },
    "H2": {
        "error": 0.008044422315310638,
        "error_type": "SEM",
        "filter_outliers_dict": {
            "filter_outliers": true,
            "iterations": 1,
            "std_devs": 2
        },
        "fit": "average",
        "modifier_error": 0.0,
        "modifier_value": 0.0,
        "value": 0.02452848479614151
    },
    "L1": {
        "error": 0.003582657170702138,
        "error_type": "SEM",
        "filter_outliers_dict": {
            "filter_outliers": true,
            "iterations": 1,
            "std_devs": 2
        },
        "fit": "average",
        "modifier_error": 0.0,
        "modifier_value": 0.0,
        "value": 0.06133852809575037
    },
    "L2": {
        "error": 0.0041737814303962496,
        "error_type": "SEM",
        "filter_outliers_dict": {
            "filter_outliers": true,
            "iterations": 1,
            "std_devs": 2
        },
        "fit": "average",
        "modifier_error": 0.0,
        "modifier_value": 0.0,
        "value": -0.03827436170925768
    }
}